[{"id":"61695227000193","label":"ELETROPAULO","shape":"box"},{"id":"62779145000190","label":"IRMANDADE STA CASA M.S.PAULO","shape":"box"},{"id":"04518462000156","label":"ACRO POSTO DE SERVI\u00c7OS E CONVI\u00c7OS  CONVENIENCIA LT","shape":"box"},{"id":"11780929000105","label":"AUTO POSTO M. M. DE AGUAI LTDA","shape":"box"},{"id":"08225043000187","label":"MARTINELI AUTO POSTO RIBEIRAO LTDA","shape":"box"},{"id":"48770051000129","label":"MIRACATU AUTO POSTO LTDA","shape":"box"},{"id":"08901079000133","label":"POSTO WEST","shape":"box"},{"id":"05130400000135","label":"CATIA CRISTINA GONCALEZ ESTEVES DE OLIVEIRA ME","shape":"box"},{"id":"10501585000187","label":"RSC EMPREENDIMENTOS MUNICIPAIS LTDA","shape":"box"},{"id":"07575651000159","label":"GOL LINHAS AEREAS INTELIGENTES","shape":"box"},{"id":"02012862000160","label":"TAM LINHA AEREAS","shape":"box"},{"id":"07046998000104","label":"TAM LINHAS AEREAS S/A","shape":"box"},{"id":"03563689000150","label":"TIM","shape":"box"},{"id":"00000000000001","label":"CELULAR FUNCIONAL","shape":"box"},{"id":"40432544000147","label":"CLARO S/A","shape":"box"},{"id":"33530486000129","label":"EMBRATEL","shape":"box"},{"id":"00000000000006","label":"RAMAL","shape":"box"},{"id":"02558157000162","label":"TELEFONICA","shape":"box"},{"id":"00000000000007","label":"CORREIOS - ENCOMENDA PAC","shape":"box"},{"id":"72629140000134","label":"HOTEL NACIONAL S/A","shape":"box"},{"id":"05013257000282","label":"INTERCITY HOTEIS INTELIGENTES","shape":"box"},{"id":"03545214000131","label":"ASSOCIA\u00c7AO DE TAXISTAS PONTO 1499","shape":"box"},{"id":"02679185000138","label":"AUTOVIAS S.A","shape":"box"},{"id":"03207703000183","label":"CONC ROD INT. PAULISTA S.A","shape":"box"},{"id":"02451848000162","label":"CONC SISTEMA  ANHANGUERA BANDEIRANTES SA","shape":"box"},{"id":"09387725000159","label":"CONCESS.DO RODOANEL OESTE S/A","shape":"box"},{"id":"46553947000120","label":"COOPERATIVA MISTA DE TRABALHO DOS MOTORISTAS AUTON","shape":"box"},{"id":"61563557000125","label":"EMPRESA DE ONIBUS PASSARO MARON LTDA","shape":"box"},{"id":"67644641000150","label":"LIDER COMUM RADIO TAXI","shape":"box"},{"id":"04088208000165","label":"PEDAGIO SEM PARAR","shape":"box"},{"id":"00524550000100","label":"PONTO DE TAXI 606","shape":"box"},{"id":"37990298000134","label":"RADIO TAXI  ALVORADA LTDA","shape":"box"},{"id":"02417464000123","label":"RENOVIAS SA","shape":"box"},{"id":"00031708000371","label":"SINDICATOS DOS CONDUTORES AUTONOMOS DE VEICULOS RO","shape":"box"},{"id":"00031708000100","label":"SINPETAXI","shape":"box"},{"id":"07424109000103","label":"SINTAXI DF","shape":"box"},{"id":"94391513000114","label":"TAXI JOAO ABOTT","shape":"box"},{"id":"09814619000104","label":"TRANSPORTE EXECUTIVO","shape":"box"},{"id":"12623662000105","label":"UNIAO DOS TAXISTAS DO DF","shape":"box"},{"id":"01594063001239","label":"VAZ ESTACIONAMENTOS LTDA","shape":"box"},{"id":"02366097000186","label":"VIANORTE","shape":"box"},{"id":"62779145000602","label":"IRMANDADE STA CASA M. S. PAULO","shape":"box"},{"id":"43751502000167","label":"IRMANDADE STA CASA M. S.PAULO","shape":"box"},{"id":"02449992005638","label":"VIVO SA","shape":"box"},{"id":"43072693000211","label":"ANIELO D AMARO E CIA LTDA","shape":"box"},{"id":"04706850000160","label":"ASTTOR AUTO POSTO LTDA","shape":"box"},{"id":"61443933000148","label":"AUTO POSTO 111 LTDA","shape":"box"},{"id":"46332896000107","label":"AUTO POSTO BARTIRA LTDA","shape":"box"},{"id":"61391546000105","label":"AUTO POSTO BELA CINTRA LTDA","shape":"box"},{"id":"53027959000187","label":"AUTO POSTO BIZUNGA LTDA","shape":"box"},{"id":"47105127000139","label":"AUTO POSTO CAIO PRADO LTDA.","shape":"box"},{"id":"62893961000120","label":"AUTO POSTO CATALAO LTDA","shape":"box"},{"id":"09657803000198","label":"AUTO POSTO CENTRO LTDA","shape":"box"},{"id":"01700156000148","label":"AUTO POSTO CHECR UP LTDA","shape":"box"},{"id":"61150876000109","label":"AUTO POSTO CISPER LTDA","shape":"box"},{"id":"07846544000118","label":"AUTO POSTO DUQUE BANDEIRANTES LTDA","shape":"box"},{"id":"60402914000100","label":"AUTO POSTO E TRANAPRTES MINUANO LTDA","shape":"box"},{"id":"03367925000163","label":"AUTO POSTO ESTRELA DE AVARE LTDA","shape":"box"},{"id":"07239339000194","label":"AUTO POSTO F.L 1 LTDA","shape":"box"},{"id":"01610670000192","label":"AUTO POSTO FRANCISCO MORATO LTDA","shape":"box"},{"id":"05468615000160","label":"AUTO POSTO GRANERO LTDA","shape":"box"},{"id":"08442236000190","label":"AUTO POSTO JOSE MARIA LISBOA LTDA","shape":"box"},{"id":"01272374000129","label":"AUTO POSTO KM 141 LTDA","shape":"box"},{"id":"04534532000160","label":"AUTO POSTO L M DE CAMPINAS LTDA","shape":"box"},{"id":"43866433000137","label":"AUTO POSTO MADALENA LTDA","shape":"box"},{"id":"06262423000166","label":"AUTO POSTO MINGO LTDA","shape":"box"},{"id":"04937358000104","label":"AUTO POSTO MISTRAL LTDA","shape":"box"},{"id":"10570911000108","label":"AUTO POSTO RIAJ LTDA","shape":"box"},{"id":"74283219000181","label":"AUTO POSTO ROTA SP LTDA.","shape":"box"},{"id":"02827078000100","label":"AUTO POSTO VERDES MARES BARRA LTDA","shape":"box"},{"id":"52476850000164","label":"AUTO POSTO ZANFORLIN LTDA","shape":"box"},{"id":"44581452000422","label":"AUTO RIO NOVO LTDA","shape":"box"},{"id":"04888013000108","label":"BG SUL PETROLEO LTDA","shape":"box"},{"id":"08316625000179","label":"CARLOS ALBERTO PAPACIDERO","shape":"box"},{"id":"00306597001683","label":"CASCOL COMBUSTIVEVEIS PARA VEICULOS LTDA","shape":"box"},{"id":"02640666000130","label":"CENTRO AUTOMOTIVO 9 DE JULHO LTDA","shape":"box"},{"id":"00715375000219","label":"COMAL COMBUSTIVEIS AUTOMOTIVOS LTDA","shape":"box"},{"id":"47359211000189","label":"COMERCIO AUTO CONTINENTAL LTDA","shape":"box"},{"id":"05459742000101","label":"CYROS AUTO SERVI\u00c7OS LTDA","shape":"box"},{"id":"72861099000399","label":"IRMAOS LONGUINI LTDA","shape":"box"},{"id":"07294058000134","label":"ITAQUAGAS AUTO POSTO LIMITADA","shape":"box"},{"id":"01943348000185","label":"JET PARK SERVI\u00c7OS  AUTOMOTIVOS LTDA","shape":"box"},{"id":"07500924000104","label":"KM 156 POSTO DE SERVI\u00c7OS AUTOMOTIVOS LTDA","shape":"box"},{"id":"05724404000141","label":"MONT BRLANC POSTO DE SERVI\u00c7OS LTDA","shape":"box"},{"id":"72620412000135","label":"MORRO AZUL COM DE PETROLEO LTDA","shape":"box"},{"id":"61344131000180","label":"POSTO DE SERVI\u00c7O TUTOIA LTDA","shape":"box"},{"id":"07766889000161","label":"POSTO DE SERVI\u00c7OS CAMBUI LTDA","shape":"box"},{"id":"02719074000108","label":"POSTO FAG E BIZARRIA DER PETROL LTDA","shape":"box"},{"id":"57569519000102","label":"POSTO GARCIA","shape":"box"},{"id":"44835866000198","label":"POSTO MAREZU","shape":"box"},{"id":"62131495000145","label":"POSTO OPALA LTDA","shape":"box"},{"id":"04595123000173","label":"POSTO TRANSO DE AGUAI LTDA","shape":"box"},{"id":"02866419000156","label":"SERV POSTO JARDIM MIRIAM","shape":"box"},{"id":"00707272000126","label":"SUNSET POSTO DE SERVI\u00c7O E CONVENIENCIA LTDA","shape":"box"},{"id":"08847260000109","label":"AUTO POSTO CASTELIMHO","shape":"box"},{"id":"09613772000173","label":"LIST WEB COMUNICA\u00c7AO & TI","shape":"box"},{"id":"04740336000141","label":"NEO GRAF  IND .GRAFICA E EDITORA LTDA","shape":"box"},{"id":"02575829000148","label":"AVIANCA","shape":"box"},{"id":"33712837000112","label":"AVIANCA","shape":"box"},{"id":"06164253000187","label":"GOL LINHAS AEREA S.A","shape":"box"},{"id":"33530486012569","label":"CLARO SA","shape":"box"},{"id":"34028316291329","label":"ECT","shape":"box"},{"id":"33450461000115","label":"ALVORADA HOTEL LTDA","shape":"box"},{"id":"04566342000205","label":"DJ HOTELARIA S/A","shape":"box"},{"id":"72180037000150","label":"EUROPA HOTEL","shape":"box"},{"id":"00679605000150","label":"GARVEY PARK HOTEL LTDA","shape":"box"},{"id":"00528877000150","label":"HOTEL DAS AMERICAS","shape":"box"},{"id":"57687022000199","label":"HOTEL NACIONAL DO BRASIL LTDA","shape":"box"},{"id":"00469171000245","label":"HOTEL PHENICIA LTDA","shape":"box"},{"id":"37069853000270","label":"MANHATTAN HOTEIS E TURISMOS LTDA","shape":"box"},{"id":"11849896000102","label":"PLANALTO BITTAR HOTEL LTDA","shape":"box"},{"id":"91046284000960","label":"PLATAMON PARTICIPACOES E EMPREENDIMENTOS LTDA","shape":"box"},{"id":"10313269000181","label":"RB3 HOTEIS","shape":"box"},{"id":"08881090000260","label":"SANTOS DUMONT INVESTIMENTO IMOBILIARIO SA","shape":"box"},{"id":"07596838000139","label":"ASSOCIACAO DOS TAXISTAS DO LARGO SAO FRANCISCO 135","shape":"box"},{"id":"02415408000150","label":"CONCESS RODOVIA OESTE DE SAO PAULO S/A","shape":"box"},{"id":"10841050000155","label":"CONCESSIONARIA DAS RODOVIAS AYRTON SENNA E CARVALH","shape":"box"},{"id":"02509491000126","label":"CONCESSIONARIA ECOVIASDOS IMIGRANTES S/A","shape":"box"},{"id":"90149071000143","label":"COOTAERO","shape":"box"},{"id":"11693334000104","label":"DEL PARK ESTACIONAMENTO","shape":"box"},{"id":"05505997000155","label":"DEL S PARK S/C LTDA","shape":"box"},{"id":"52378239000101","label":"GUARUCOOP TAXI AEROPORTO SERVI\u00c7O CREDENCIADO","shape":"box"},{"id":"44581056000152","label":"MANOEL RODRIGUES","shape":"box"},{"id":"02404819000140","label":"MARECHAL CAMARA TAXI","shape":"box"},{"id":"11439901000109","label":"MT MANCHETE TAXI","shape":"box"},{"id":"10531501000239","label":"PO1 PIRATININGA SAU 08007730090","shape":"box"},{"id":"45992724002574","label":"RAPIDO CAMPINAS","shape":"box"},{"id":"45992724000105","label":"RAPIDO LUXO CAMPINAS LTDA","shape":"box"},{"id":"03025305000146","label":"RENOVIA","shape":"box"},{"id":"10678505000163","label":"RODOVIA SP 300","shape":"box"},{"id":"03497792000140","label":"RODOVIAS INTEGRADAS DO OESTE S/A","shape":"box"},{"id":"10712647000108","label":"SIA TAXI","shape":"box"},{"id":"33725029000190","label":"TRANSCOOPASS RADIO TAXI","shape":"box"},{"id":"36095792000172","label":"TRANSCOOTOUR TAXI ESPECIAL","shape":"box"},{"id":"61084018000103","label":"VIA\u00c7AO COMETA","shape":"box"},{"id":"10635691000153","label":"VIARONDON","shape":"box"},{"id":"05730375000120","label":"Cia A\u00e9rea - WEBJET","shape":"box"},{"id":2441369806.0,"label":"Paulo Teixeira","shape":"circle"}]