[{"id":"13365361000183","label":"ANTONIO JOSE RAIMUNDO DE MORAIS","shape":"box"},{"id":"05972646000235","label":"BATE INFORMATICA","shape":"box"},{"id":"63939607000151","label":"CIA.DO SOFTWARE","shape":"box"},{"id":"06840748000189","label":"ELETROB\u00c1S DISTRIBUI\u00c7\u00c3O PIAU\u00cd","shape":"box"},{"id":"01102311391","label":"MARIA IRACEMA  DO VALE MENDES","shape":"box"},{"id":"00608874000126","label":"MM ENFORMATICA LTDA","shape":"box"},{"id":"12132854000100","label":"PAPELARIA E ESCRITORIO","shape":"box"},{"id":"34977223000478","label":"AUTO \u00b4POSTO CONFIAN\u00c7A LTDA","shape":"box"},{"id":"02731610000271","label":"AUTO HITCAR","shape":"box"},{"id":"37106895000153","label":"AUTO POSTO 107 SUL LTDA","shape":"box"},{"id":"03530749000139","label":"AUTO POSTO 314 NORTE LTDA","shape":"box"},{"id":"08202116000115","label":"AUTO POSTO AEROPORTO LTDA","shape":"box"},{"id":"05901688000102","label":"AUTO POSTO DOMINGOS","shape":"box"},{"id":"00000042000122","label":"AUTO POSTO GASOL LTDA","shape":"box"},{"id":"00000042001013","label":"AUTO POSTO GASOL LTDA","shape":"box"},{"id":"03482208000182","label":"AUTO POSTO JK LTDA","shape":"box"},{"id":"00647440000135","label":"AUTO SHOPPING QL 06","shape":"box"},{"id":"00097626000320","label":"BRASAL COMBUST\u00cdVEIS","shape":"box"},{"id":"00373589000254","label":"CAL COMBUST\u00cdVEIS  AUTOMOTIVOS LTDA","shape":"box"},{"id":"00661132000750","label":"CANA\u00c3 COMBUST\u00cdVEIS P VE\u00cdCULOS LTDA","shape":"box"},{"id":"00306597001411","label":"CASCOL COMBUST\u00cdVEIS","shape":"box"},{"id":"00306597000105","label":"CASCOL COMBUST\u00cdVEIS PARA VE\u00cdCULOS LTDA","shape":"box"},{"id":"00306597000520","label":"CASCOL COMBUST\u00cdVEIS PARA VE\u00cdCULOS LTDA","shape":"box"},{"id":"10702904000112","label":"COMERCIAL DE COMBUST\u00cdVEL MAM LTDA","shape":"box"},{"id":"00038505000579","label":"CONVER COMBUST\u00cdVEIS  AUTOMOTIVOS LTDA","shape":"box"},{"id":"00038505000145","label":"CONVER COMBUST\u00cdVEIS AUTOMOTIVOS LTDA","shape":"box"},{"id":"00038505000730","label":"CONVER COMBUST\u00cdVEIS AUTOMOTIVOS LTDA","shape":"box"},{"id":"00038505000307","label":"CONVER COMBUSTVEIS AUTOMOTIVOS LTDA","shape":"box"},{"id":"26991067000129","label":"CRUZEIRO COMBUST\u00cdVEIS E SERVI\u00c7O S/A","shape":"box"},{"id":"00044347000136","label":"IGREJINHA COMBUST\u00cdVEIS","shape":"box"},{"id":"00358192000102","label":"IGREJINHA COMBUSTIVEL","shape":"box"},{"id":"06664585000635","label":"KING PETROLEO LTDA","shape":"box"},{"id":"00038463000304","label":"LUBRIFICANTES GASOL INDUSTRIA E COMERCIO LTDA","shape":"box"},{"id":"02989654000468","label":"MELHOR POSTO DE COMBUST\u00cdVEIS  LTDA","shape":"box"},{"id":"02989654001197","label":"MELHOR POSTO DE COMBUST\u00cdVEIS LTDA","shape":"box"},{"id":"04249989000122","label":"NAILTON PASSOS & CIA COMERCIO DE PETROLEO LTDA","shape":"box"},{"id":"05158335000156","label":"POSTO 109 SUL DERIVALDOS DE PETROLEO LTDA","shape":"box"},{"id":"04473193000159","label":"POSTO DA TORRE LTDA","shape":"box"},{"id":"08596605000107","label":"POSTO HOMERO CASTELO BRANCO","shape":"box"},{"id":"61454393000106","label":"POSTO IMPERIAL","shape":"box"},{"id":"06833040000109","label":"POSTO IPANEMA LTDA","shape":"box"},{"id":"00314831000138","label":"POSTO ITAMARATY LTDA","shape":"box"},{"id":"02760727000283","label":"POSTO JUNCO LTDA","shape":"box"},{"id":"05454390000193","label":"POSTO MONUMENTAL","shape":"box"},{"id":"10336626000127","label":"POSTO NOSSA SENHORA DE FATIMA","shape":"box"},{"id":"05907293000109","label":"POSTO SEIS","shape":"box"},{"id":"00031708000371","label":"SINPETAXI","shape":"box"},{"id":"41284019000194","label":"MCM SISTEMAS","shape":"box"},{"id":"07961379000145","label":"J C S HOLANDA-ME","shape":"box"},{"id":"03548155000155","label":"M\u00cdDIA EXTERNA  LTDA","shape":"box"},{"id":"00366120000107","label":"DIPREL","shape":"box"},{"id":"01526415000328","label":"COPA AIRLINES","shape":"box"},{"id":"07575651000159","label":"GOL LINHAS A\u00c9REAS INTELIGENTE","shape":"box"},{"id":"06164253000187","label":"GOL LINHAS A\u00c9REAS INTELIGENTE  S/A","shape":"box"},{"id":"02012862000160","label":"TAM","shape":"box"},{"id":"04114985000137","label":"TOP LINE T\u00c1XI A\u00c9REO","shape":"box"},{"id":"33530486000129","label":"EMPRESA BRASILE DE TELECOMUNICA\u00c7\u00c3O S/A","shape":"box"},{"id":"33530486005945","label":"EMPRESA BRASILEIRA DE TELECOMUNICA\u00c7\u00c3ES S/A","shape":"box"},{"id":"00000000000003","label":"IM\u00d3VEL FUNCIONAL","shape":"box"},{"id":"00000000000006","label":"RAMAL","shape":"box"},{"id":"33000118000179","label":"TELEMAR NORTE LESTE S/A","shape":"box"},{"id":"33000118001060","label":"TELEMAR NORTE LESTE S/A","shape":"box"},{"id":"04206050008084","label":"TIM","shape":"box"},{"id":"04206050005140","label":"TIM CELULAR","shape":"box"},{"id":"00000000000007","label":"CORREIOS - CARTA COMERCIAL","shape":"box"},{"id":"38059507000436","label":"ALFA ADMINISTRADORA E PARTICIPA\u00c7\u00c3OES LTDA","shape":"box"},{"id":"42591651010530","label":"ARCOS DOURADOS COMERC DE ALIMENTATOS LTDA","shape":"box"},{"id":"00073478000141","label":"BIERFASS","shape":"box"},{"id":"00691317000111","label":"CARLOTA ALIMENTOS LTDA","shape":"box"},{"id":"10620620000187","label":"CHURRASCARIA RESID\u00caNCIA VII","shape":"box"},{"id":"31611189000263","label":"CINEMAS PARIS SEVERIANO RIBEIRO LTDA","shape":"box"},{"id":"06204320000140","label":"CLS RESTAURANTE BRASILIA LTDA","shape":"box"},{"id":"11197839000188","label":"DEVASSA GLERSY ALINMENTOS LTDA","shape":"box"},{"id":"72614977000290","label":"EMPREENDIMENTOS E ALIMENTA\u00c7\u00c3O LTDA","shape":"box"},{"id":"08962032000180","label":"FRAN'S CAFE","shape":"box"},{"id":"04021583000198","label":"FRATELLO UNO DUVAN BAR E RESTAURANTE LTDA","shape":"box"},{"id":"47396635000202","label":"H.M HOTEIS & TURISMO S/A","shape":"box"},{"id":"07491982000100","label":"HAWAI GRILL","shape":"box"},{"id":"08257028000110","label":"LUCKYSTON RESTAURANTE LTDA","shape":"box"},{"id":"00827430000181","label":"MALAGUETTA BAR E RESTAURANTE","shape":"box"},{"id":"01019348000193","label":"MINUTA BUFFET","shape":"box"},{"id":"07586015000122","label":"OLIVER COMERCIO DE ALIMENTOS LTDA","shape":"box"},{"id":"04889116000184","label":"PIZZA CESAR","shape":"box"},{"id":"17314329000553","label":"RA CATERING LTDA","shape":"box"},{"id":"01297109000103","label":"RESTAURANTE DONA MARIA LTDA MEE","shape":"box"},{"id":"73152340000454","label":"RESTAURANTE GERO LTDA","shape":"box"},{"id":"44024297000109","label":"RESTAURANTES TOURNEGRILL LTDA","shape":"box"},{"id":"62505847002390","label":"RGB RESTAURANTES LTDA","shape":"box"},{"id":"33469172000672","label":"SER.NAS. DE APRENDIZAGEM COMERCIAL SENAC","shape":"box"},{"id":"09209754000120","label":"SUSHILOKO COMERCIO DE ALIMENTA\u00c7\u00c3O LTDA-EPP","shape":"box"},{"id":"11042998000103","label":"SUSHILOKO LB. COMERCIO DE ALIMENTOS LTDA","shape":"box"},{"id":"09612226000118","label":"TOUJOURS","shape":"box"},{"id":"11869345000100","label":"VALENTINA","shape":"box"},{"id":"04514473000168","label":"VELOCE MASSAS  LTDA","shape":"box"},{"id":"01322793000128","label":"BRISA AMAR HOTEL S/A","shape":"box"},{"id":"02238702000214","label":"CASTOR & LEAO ADMINISTRA\u00c7AO HOTELEIRA S/A","shape":"box"},{"id":"10660342000191","label":"3R AG\u00caNCIA DE VE\u00cdCULOS E PASSAGENS A\u00c9REAS LTDA","shape":"box"},{"id":"46553947000120","label":"COOPERATIVA MOTORISTA  TAXI","shape":"box"},{"id":"06912773000120","label":"ECO R\u00c1DIO T\u00c1XI","shape":"box"},{"id":"11359991000110","label":"GM EFICI\u00caNCIA E SEGURAN\u00c7A","shape":"box"},{"id":"67644641000150","label":"LIDER TAXE","shape":"box"},{"id":"11951173000101","label":"PRISMA","shape":"box"},{"id":"05730375000120","label":"Cia A\u00e9rea - WEBJET","shape":"box"},{"id":4248139715.0,"label":"HUGO NAPOLE\u00c3O","shape":"circle"}]