[{"id":"28410074000115","label":"ATACADO SAO PAULO LTDA","shape":"box"},{"id":"05430734000124","label":"CENTRAL CARTUCHO LTDA ME","shape":"box"},{"id":"09198002000101","label":"COMERCIAL ALFA LTDA ME","shape":"box"},{"id":"28152650000171","label":"ESCELSA ESPIRITO SANTO CENTRAIS ELETRICAS S.A","shape":"box"},{"id":"27238815000402","label":"GECORE COMERCIAL DISTRIBUIDORA LTDA","shape":"box"},{"id":"08403456000104","label":"HELP CARTUCHOS PAPELARIA SER. LTDA","shape":"box"},{"id":"00943736000101","label":"PANTEON IMOVEIS","shape":"box"},{"id":"08775011000155","label":"POINT COMPUTADORES","shape":"box"},{"id":"23957236000205","label":"PORT PAPELARIA ESCRIT. E INFORMATICA LTDA","shape":"box"},{"id":"04560471000296","label":"R.F.G DUARTE PAPELARIA LTDA","shape":"box"},{"id":"27419142000144","label":"POSTO IATE LTDA","shape":"box"},{"id":"04228463000166","label":"AGFS DERIVADOS DE PETROLEO LTDA","shape":"box"},{"id":"04145589000681","label":"ARARA AZUL REDE DE POSTOS","shape":"box"},{"id":"04145589000177","label":"ARARA AZUL REDE DE POSTOS LTDA","shape":"box"},{"id":"04145589000258","label":"ARARA AZUL REDE DE POSTOS LTDA","shape":"box"},{"id":"04145589001149","label":"ARARA AZUL REDE DE POSTOS LTDA","shape":"box"},{"id":"04145589001491","label":"ARARA AZUL REDE DE POSTOS LTDA","shape":"box"},{"id":"31474018000159","label":"AUTO POSTO CIVIT LTDA","shape":"box"},{"id":"00690555000102","label":"AUTO POSTO DA ILHA LTDA","shape":"box"},{"id":"02731610000271","label":"AUTO POSTO ITICAR LTDA","shape":"box"},{"id":"00629129000163","label":"AUTO POSTO MIRAMAR LTDA","shape":"box"},{"id":"12535572000154","label":"AUTO POSTO MORADA LTDA","shape":"box"},{"id":"32492498000143","label":"AUTO POSTO OLIVA LTDA","shape":"box"},{"id":"27019108000182","label":"AUTO POSTO PEDREIRAS LTDA","shape":"box"},{"id":"39400494000137","label":"AUTO POSTO PRESIDENTE LTDA","shape":"box"},{"id":"05032428000130","label":"AUTO POSTO RETA GRANDE LTDA","shape":"box"},{"id":"30541940000159","label":"AUTO POSTO SELEMAR LTDA","shape":"box"},{"id":"04361389000151","label":"AUTO POSTO WAVE LTDA","shape":"box"},{"id":"39383880000168","label":"AUTO SERVI\u00c7O AEROPORTO LTDA","shape":"box"},{"id":"28048312000194","label":"AUTO SERVI\u00c7O CANAA LTDA","shape":"box"},{"id":"05684518000105","label":"AUTO SERVI\u00c7O GASVIX LTDA","shape":"box"},{"id":"37063328001309","label":"AUTO SHOPPING DERIVADOS DE PETROLEO LTDA","shape":"box"},{"id":"00097626000320","label":"BRASAL COMBUSTIVEIS LTDA","shape":"box"},{"id":"00097626000400","label":"BRASAL COMBUSTIVEIS LTDA","shape":"box"},{"id":"03811983000134","label":"BRENT PETROLEO LTDA","shape":"box"},{"id":"00373589000416","label":"CAL COMBUSTIVEIS AUTOMOTIVOS LTDA","shape":"box"},{"id":"00611875000120","label":"COMERCIAL RALORI LTDA","shape":"box"},{"id":"32426165000116","label":"DIPETROL COM. DERIV. DE PETROLEO LTDA","shape":"box"},{"id":"05738923000169","label":"GEGEL AUTO POSTO LTDA","shape":"box"},{"id":"27025907000161","label":"INCAP INDUSTRIA COMER\u00c7IO AGRO PECUARIO LTDA","shape":"box"},{"id":"08788618000170","label":"J . S PETROLEO E COMERCIO LTDA","shape":"box"},{"id":"05937132000168","label":"JOSE GUASTI NETO","shape":"box"},{"id":"28430270000151","label":"LUIZ CEOLIN E FILHOS LTDA","shape":"box"},{"id":"36380038000184","label":"MACAL COMERCIAL LTDA","shape":"box"},{"id":"47427653006741","label":"MAKHO ATACADISTA S/A","shape":"box"},{"id":"02947371000100","label":"MARKBEL REVEND. DE PETROLEO LTDA","shape":"box"},{"id":"02989654001197","label":"MELHOR POSTO DE COMBUST. LTDA","shape":"box"},{"id":"34274233002814","label":"PETROBRAS DISTRIBUIDORA S/A","shape":"box"},{"id":"02072286000650","label":"PETROIL COMBUSTIVEIS LTDA","shape":"box"},{"id":"03028906000102","label":"POLUS COMERCIO E SERVICO LTDA","shape":"box"},{"id":"10484697000177","label":"POSTO 2F LTDA","shape":"box"},{"id":"08202116000115","label":"POSTO AEROPORTO LTDA","shape":"box"},{"id":"27734094000189","label":"POSTO ATLANTICO LTDA","shape":"box"},{"id":"31709116000128","label":"POSTO CAMBURI DO GAS LTDA","shape":"box"},{"id":"05393247000139","label":"POSTO CANOA DERIVADOS DE PETROLEO LTDA","shape":"box"},{"id":"00375386000116","label":"POSTO CEASA","shape":"box"},{"id":"31772304000109","label":"POSTO COSTA AZUL LTDA","shape":"box"},{"id":"02922895000147","label":"POSTO DE COMBUSTIVEIS MIRANDA LTDA","shape":"box"},{"id":"07470392000100","label":"POSTO DE COMBUSTIVEIS OTAVIO LTDA","shape":"box"},{"id":"02923967000170","label":"POSTO DE SERVI\u00c7O SERRA LINDA LTDA","shape":"box"},{"id":"10750039000180","label":"POSTO DISBRAVE IMPERIAL LTDA","shape":"box"},{"id":"11368640000175","label":"POSTO DIVINO LTDA","shape":"box"},{"id":"08212395000106","label":"POSTO GENTIL FUNDAO LTDA","shape":"box"},{"id":"39330410000136","label":"POSTO ITAPARICA LTDA","shape":"box"},{"id":"03458109000165","label":"POSTO LIFE LTDA","shape":"box"},{"id":"31738883000165","label":"POSTO PARADA IBIRA\u00c7U LTDA","shape":"box"},{"id":"01917233000116","label":"POSTO SANTA GEMA LTDA","shape":"box"},{"id":"04994796000104","label":"POSTO SB LTDA","shape":"box"},{"id":"01514752000133","label":"POSTO THIAGO LTDA","shape":"box"},{"id":"27023308000109","label":"POSTO TRIANGULO LTDA","shape":"box"},{"id":"05102856000434","label":"REDE AMIGOS LTDA","shape":"box"},{"id":"27226612000153","label":"SEPEL SERRA PETROLEOS LTDA","shape":"box"},{"id":"28039519000100","label":"SERVICENTRO SERRANO LTDA","shape":"box"},{"id":"02488651000106","label":"FELIPE & ALMEIDA ADVOGADOS","shape":"box"},{"id":"12513918000113","label":"VIVA VOTOS COMUNICA\u00c7AO INTEGRADA LTDA ME","shape":"box"},{"id":"06190606000113","label":"FLAVIA MIGNONI COMUNICA\u00c7\u00c3O E MARKETING LTDA","shape":"box"},{"id":"27252147000125","label":"GRAFICA E EDITORA JEP LTDA","shape":"box"},{"id":"07156900000171","label":"NEWGATE INFORMARTICA LTDA","shape":"box"},{"id":"81687052700","label":"AUDIFAX  BARCELOS","shape":"box"},{"id":"07575651000159","label":"VARIG","shape":"box"},{"id":"00000000000001","label":"CELULAR FUNCIONAL","shape":"box"},{"id":"00000000000006","label":"RAMAL","shape":"box"},{"id":"33000118000250","label":"TELEMAR NORTE LESTE S/A","shape":"box"},{"id":"33000118000179","label":"TELEMAR NORTE LESTE S/A OI FIXO","shape":"box"},{"id":"02449992008149","label":"VIVO S.A","shape":"box"},{"id":"00000000000007","label":"CORREIOS - CARTA REGISTRADA COM AR","shape":"box"},{"id":"32405193000157","label":"CT. EMP. BRAS. DE CORREIOS E TELEGRAFOS","shape":"box"},{"id":"39379375000140","label":"ECT - EMP. BRAS. CORREIOS E TELEGRAFOS","shape":"box"},{"id":"39627724000103","label":"ECT - EMP. BRAS. CORREIOS E TELEGRAFOS","shape":"box"},{"id":"34028316500343","label":"ECT. EMP. BRAS. CORREIOS ETELEGRAFOS","shape":"box"},{"id":"27065150000130","label":"NASSAU EDITORA RADIO E TV LTDA","shape":"box"},{"id":"03687592000150","label":"VALOR ECONOMICO S/A","shape":"box"},{"id":"01514749000110","label":"A D M  CHURRASCARIA LTDA","shape":"box"},{"id":"11298042000177","label":"AGR COMERCIAL LTDA","shape":"box"},{"id":"12864038000191","label":"ALVES, EUCLIDES E CIA LTDA","shape":"box"},{"id":"42591651138501","label":"ARCOS DOURADOAS COM. DE ALIMENTOS LTDA","shape":"box"},{"id":"42591651082603","label":"ARCOS DOURADOS COM DE ALIMENTOS LTDA","shape":"box"},{"id":"42591651098950","label":"ARCOS DOURADOS COM. DE ALIMENTOS LTDA","shape":"box"},{"id":"42591651104941","label":"ARCOS DOURADOS COMER. DE ALIMENTOS LTDA","shape":"box"},{"id":"54393046010614","label":"ARRAS COMERCIO DE ALIMENTOS LTDA","shape":"box"},{"id":"07309877000108","label":"BOM PAO BEZERRA COM. LTDA","shape":"box"},{"id":"12840475000175","label":"BRASIL ICE LTDA","shape":"box"},{"id":"07711619000153","label":"BSB ADV TUR EVENTOS E PAS. NAUTICOS LTDA","shape":"box"},{"id":"05678778000178","label":"CAFE AEROPORTO LTDA","shape":"box"},{"id":"09290876000194","label":"CAFETERIA E CONF. AMENDOEIRAS LTDA","shape":"box"},{"id":"01323420000171","label":"CANTINA DA MASSA LTDA","shape":"box"},{"id":"00660993000128","label":"CHURRASCARIA ESPETO DE OURO","shape":"box"},{"id":"05019403000104","label":"COMFEITARIA  JARDINS LTDA","shape":"box"},{"id":"05233063000101","label":"COMIDAS REGIONAIS DO BRASIL LTDA","shape":"box"},{"id":"05399750000100","label":"CONVENIENCE SHOPPING E CAFETERIA","shape":"box"},{"id":"39325840000160","label":"COZITA RESTAURANTE LTDA","shape":"box"},{"id":"28395739000169","label":"DEBONIS D.S E B REST. LTDA","shape":"box"},{"id":"13584886000100","label":"G.V ECCHER DELIVERY- ME","shape":"box"},{"id":"03997010000131","label":"GERALDO RESTAURANTE LTDA","shape":"box"},{"id":"02905110011758","label":"GR S/A","shape":"box"},{"id":"07642860000178","label":"K B COMERCIO DE ALIMENTO LTDA","shape":"box"},{"id":"06092105000102","label":"LAKESIDE CONVENIENCE","shape":"box"},{"id":"31474240000151","label":"MAGAZINE ZORTEA SANTUZZI LTDA","shape":"box"},{"id":"01019348000193","label":"MINUTA BUFFET  REST. SENADO","shape":"box"},{"id":"00984060000277","label":"NATURETO RESTAURANTE NATURAL","shape":"box"},{"id":"07912236000143","label":"POUSADA AGUAS DE PINON LTDA","shape":"box"},{"id":"10503248000129","label":"REST. E SERV. DERRA GRANDE LTDA","shape":"box"},{"id":"10490981000156","label":"RESTAURANTE ENSEADA DE MANGUINHOS LTDA","shape":"box"},{"id":"33469172001644","label":"SER. NAC. DE APREND. COM. SENAC","shape":"box"},{"id":"33469172000672","label":"SERV. DE APREND. COMERCIAL SENAC","shape":"box"},{"id":"26179374000100","label":"SUCOS E ASSADOS LTDA","shape":"box"},{"id":"03496049000175","label":"TB ALIMENTOS BRASILIA LTDA","shape":"box"},{"id":"02223966002671","label":"ATLANTICA HOTELS INTERNACIONAL BRASIL LTDA","shape":"box"},{"id":"09850173000173","label":"VILA RICA HOTEL HOTEIS PERNAMBUCO S.A","shape":"box"},{"id":"28789584000145","label":"COOP. TRAB. MOT. AUT. DE TAXI R.J COOPATUR","shape":"box"},{"id":"10892621000180","label":"KAPPER ALUGUEL DE VEICULOS S/A","shape":"box"},{"id":"00031708000371","label":"SIND. PERM.DE TAXI MOT. AUX. D.F  SINPETAXI","shape":"box"},{"id":"39825047000120","label":"VETRAN  TRANSP. LEVES E LOCA. VEICULOS LTDA","shape":"box"},{"id":"09296295000160","label":"Cia A\u00e9rea - AZUL","shape":"box"},{"id":"02012862000160","label":"Cia A\u00e9rea - TAM","shape":"box"},{"id":"02428624000130","label":"Cia A\u00e9rea - TRIP","shape":"box"},{"id":"05730375000120","label":"Cia A\u00e9rea - WEBJET","shape":"box"},{"id":81687052700.0,"label":"AUDIFAX","shape":"circle"}]