[{"id":"15139629000194","label":"coelba","shape":"box"},{"id":"00895371000189","label":"COMTECH INFORMATICA LTDA","shape":"box"},{"id":"13281747000107","label":"condominio mundo plaza","shape":"box"},{"id":"43283811005976","label":"Kalunga Com.  e Ind. Gr\u00e1fica Ltda.","shape":"box"},{"id":"03170623000109","label":"OMNI ESTACIONAMENTOS LTDA","shape":"box"},{"id":"13927801000149","label":"PREFEITURA DO SALVADOR","shape":"box"},{"id":"00286669501","label":"RISONAIDE MARIA DA CRUZ","shape":"box"},{"id":"97528237000181","label":"UNIADONAI COMERCIO VAREJISTA LTDA","shape":"box"},{"id":"08202116000115","label":"AUTO POSTO AEROPORTO LTDA","shape":"box"},{"id":"00647440000135","label":"Auto Shopping QL 06 - Com. de Der. de Petroleo LTDA","shape":"box"},{"id":"38053450000115","label":"BR 070 COM\u00c9RCIO DE DERIVADOS DE PETR\u00d3LEO LTDA","shape":"box"},{"id":"15019152000103","label":"BRASPETRO COMERCIO DE COMBUST\u00cdVEIS LTDA","shape":"box"},{"id":"00306597003112","label":"CASCOL COMBUSTIVEIS","shape":"box"},{"id":"00306597007290","label":"CASCOL COMBUSTIVEIS PARA VEICULOS LTDA","shape":"box"},{"id":"00543213000240","label":"DISBRAVE COMBUSTIVEIS LTDA","shape":"box"},{"id":"02072286000650","label":"PETROIL COMBUSTIVEIS LTDA","shape":"box"},{"id":"05401860000150","label":"pOSTO aMORIM & aMORIM","shape":"box"},{"id":"10459168000113","label":"POSTO AVENIDA H\u00c9LIO PRATES LTDA","shape":"box"},{"id":"05084588000122","label":"POSTO COMERCIAL NORTE LTDA.","shape":"box"},{"id":"04473193000159","label":"POSTO DA TORRE LTDA","shape":"box"},{"id":"10750039000180","label":"POSTO DISBRAVE IMPERIAL","shape":"box"},{"id":"13578265000113","label":"POSTO MATARIPE ABASTECIMENTOS E SERVI\u00c7OS LTDA","shape":"box"},{"id":"13578265000547","label":"POSTO MATARIPE POSTOS MATARIPE ABASTECIMENTOS E SERVI\u00c7OS LTDA","shape":"box"},{"id":"00306597002493","label":"Posto Petrobras","shape":"box"},{"id":"13578265001276","label":"POSTOS MATARIPE ABASTECIMENTOS E SERV LTDA","shape":"box"},{"id":"13578265001357","label":"POSTOS MATARIPE ABASTECIMENTOS E SERVI\u00c7OS LTDA","shape":"box"},{"id":"13578265001519","label":"POSTOS MATARIPE ABASTECIMENTOS E SERVI\u00c7OS LTDA","shape":"box"},{"id":"13578265001780","label":"POSTOS MATARIPE ABASTECIMENTOS E SERVI\u00c7OS LTDA","shape":"box"},{"id":"13302066000188","label":"VARJAO CLIPPING LTDA - ME","shape":"box"},{"id":"05348012000125","label":"COM'ART COMUNICA\u00c7\u00c3O E PUBLICIDADE LTDA","shape":"box"},{"id":"13983873000103","label":"M DA S CAZUQUEL DESENVOLVIMENTO WEB - ME","shape":"box"},{"id":"00000000000001","label":"CELULAR FUNCIONAL","shape":"box"},{"id":"00000000000003","label":"IM\u00d3VEL FUNCIONAL","shape":"box"},{"id":"05423963015305","label":"OI","shape":"box"},{"id":"05423963000111","label":"OI M\u00d3VEL S.A","shape":"box"},{"id":"00000000000006","label":"RAMAL","shape":"box"},{"id":"02558157000162","label":"Telef\u00f4nica Brasil S.A.","shape":"box"},{"id":"33000118000179","label":"TELEMAR NORTE LESTE","shape":"box"},{"id":"33000118000500","label":"TELEMAR NORTE LESTE S/A","shape":"box"},{"id":"04164616000400","label":"TNL PCS S.A","shape":"box"},{"id":"00000000000007","label":"CORREIOS - CARTA COMERCIAL","shape":"box"},{"id":"42004556000104","label":"PRISCILA DIAS REIS -ME","shape":"box"},{"id":"14536515000115","label":"BECO COMERCIO DE ALIMENTOS LTDA","shape":"box"},{"id":"10657603000114","label":"CASSIMIRO","shape":"box"},{"id":"10580005000356","label":"CENTRAL PARK RESTAURANTE E EVENTOS LTDA ME","shape":"box"},{"id":"05230170000186","label":"DU CHEFF RESTAURANTE","shape":"box"},{"id":"37124724000157","label":"GREEN'S COM\u00c9RCIO DE ALIMENTOS LTDA EPP","shape":"box"},{"id":"16631363000165","label":"le vian panificadora","shape":"box"},{"id":"00683748000136","label":"MARIETTA COM\u00c9RCIO DE ALIMENTOS","shape":"box"},{"id":"10923812000162","label":"MARZUK COM. DE ALIMENTOS LTDA ME","shape":"box"},{"id":"11869345000100","label":"NAPOLITANA COMERCIO DE ALIMENTOS LTDA - ME","shape":"box"},{"id":"37994878000108","label":"RESTAURANTE SALADA MISTA LTDA-EPP","shape":"box"},{"id":"33469172000672","label":"SERV. NAC. DE APRENDIZAGEM COMERCIAL - SENAC","shape":"box"},{"id":"05266391000295","label":"BONOTEL ADMINISTRADORA DE HOTEIS LTDA","shape":"box"},{"id":"33742164000143","label":"EVEREST RIO HOTEL S/A","shape":"box"},{"id":"07881411000182","label":"ITEM HOTELARIA TURISMO ESTACIONAMENTO P/ VEICULOS LTDA - ME","shape":"box"},{"id":"14674451000119","label":"ATA - AEROTAXI ABAET\u00c9 LTDA.","shape":"box"},{"id":"04637565000135","label":"INLOCA LOCA\u00c7\u00c3O DE EQUIPAMENTOS LTDA","shape":"box"},{"id":"07560370000122","label":"A. R VENANCIO","shape":"box"},{"id":"18993304000243","label":"ALFA PARK ADMIN DE  ESTACIONAMENTO LTDA","shape":"box"},{"id":"60537263089981","label":"ALLPARK EMPREENDIMENTOS PARTICIPA\u00c7\u00d5ES E SERVI\u00c7OS SA","shape":"box"},{"id":"33725029000190","label":"COOPERATIVA DE TRABAL DE MOTORISTAS DE VEIC DE TRANSPORTE DE PASSAGEIROS E TURISMO DO RIO DE JANEIRO","shape":"box"},{"id":"48549331000101","label":"COOPERTAXI - COOP DOS CONDUTORES AUTONOMOS DE VEIC","shape":"box"},{"id":"52378239000101","label":"GUARUCOOP T\u00c1XI AEROPORTO","shape":"box"},{"id":"00524550000100","label":"PONTO DE TAXI - 606 - A.M.T.C.A.C","shape":"box"},{"id":"11257173000106","label":"S\u00c3O CONRADO T\u00c1XI","shape":"box"},{"id":"00031708000100","label":"SINPETAXI - DF","shape":"box"},{"id":"07424109000103","label":"SINTAXI - DF","shape":"box"},{"id":"00986427000100","label":"SULATAXI","shape":"box"},{"id":"07384726000114","label":"VALE TAXI COOP","shape":"box"},{"id":"02575829000148","label":"Cia A\u00e9rea - AVIANCA","shape":"box"},{"id":"09296295000160","label":"Cia A\u00e9rea - AZUL","shape":"box"},{"id":"07575651000159","label":"Cia A\u00e9rea - GOL","shape":"box"},{"id":"02012862000160","label":"Cia A\u00e9rea - TAM","shape":"box"},{"id":2372967568.0,"label":"ANTONIO IMBASSAHY","shape":"circle"}]