[{"id":"04825365515","label":"CARLOS EGIMA LOPES DA SILVA","shape":"box"},{"id":"11050845000108","label":"MIXPEL INFORM\u00c1TICA","shape":"box"},{"id":"09377850000188","label":"ML PIMENTA DA CUNHA","shape":"box"},{"id":"01344029000153","label":"PAQU\u00ca PAPELARIA LTDA","shape":"box"},{"id":"06101159000189","label":"AUTO POSTO GRUTA LTDA","shape":"box"},{"id":"05254310000318","label":"AUTO POSTO LIDERAN\u00c7A 2","shape":"box"},{"id":"10496030000194","label":"Auto Posto Serrinha","shape":"box"},{"id":"05254310000156","label":"LIDERAN\u00c7A COM E DISTRIB. DE COMB LTDA","shape":"box"},{"id":"70090972000108","label":"NASHE LTDA","shape":"box"},{"id":"02072286000650","label":"PETROIL COMBUSTIVEIS LTDA","shape":"box"},{"id":"18928595000105","label":"POSTO CRADOSO","shape":"box"},{"id":"14004969000145","label":"WALTER SAMMYR VELOSO DE CARVALHO","shape":"box"},{"id":"04487560000173","label":"ALTAIR DOS SANTOS","shape":"box"},{"id":"01060832000166","label":"ET. Empreendimento de Comunica\u00e7\u00e3o","shape":"box"},{"id":"00000000000003","label":"IM\u00d3VEL FUNCIONAL","shape":"box"},{"id":"05423963013957","label":"OI MOVEL S.A.","shape":"box"},{"id":"00000000000006","label":"RAMAL","shape":"box"},{"id":"02558157000162","label":"Telef\u00f4nica Brasil S.A. - VIVO","shape":"box"},{"id":"02558157001215","label":"Telefonica Brasil SA","shape":"box"},{"id":"04206050000180","label":"TIM CELULAR S.A.","shape":"box"},{"id":"04206050005140","label":"TIM CELULAR S/A","shape":"box"},{"id":"04206050008165","label":"TIM CELULAR SA","shape":"box"},{"id":"04164616001392","label":"TNL PCS S.A","shape":"box"},{"id":"00000000000007","label":"CORREIOS - CARTA COMERCIAL","shape":"box"},{"id":"02012862001131","label":"TAM CARGO","shape":"box"},{"id":"02012862003347","label":"TAM CARGO","shape":"box"},{"id":"15715233000148","label":"ALL COOK INDUSTRIA E COMERCIO LTDA","shape":"box"},{"id":"08388439000145","label":"ANDR\u00c9 DE P. P. ALBUQUERQUE","shape":"box"},{"id":"86894953001219","label":"BIGBURGER SALVADOR LANCHONETES LTDA","shape":"box"},{"id":"10580005000356","label":"CENTRAL PARK RESTAURANTE E EVENTOS LTDA ME","shape":"box"},{"id":"08698712000138","label":"DEBORAH NATALIA G. DE FREITAS REST-ME","shape":"box"},{"id":"02801222000210","label":"DOLCE BRUNO LTDA","shape":"box"},{"id":"17572266000101","label":"JULIANO E TEIXEIRA  COM. DE ALIMENTOS LTDA - ME","shape":"box"},{"id":"13830432000171","label":"LOPES E MEDEIROS RESTAURANTE LTDA - ME","shape":"box"},{"id":"08345087000140","label":"Master Food Macei\u00f3 Ltda","shape":"box"},{"id":"04886969002963","label":"R & P EMPREENDIMENTOS ALIMENTICIOS LTDA","shape":"box"},{"id":"17314329004460","label":"Ra Catering","shape":"box"},{"id":"14755547000101","label":"RESTAURANTE BICHO DO MAR PRAIA LTDA - ME","shape":"box"},{"id":"33469172001644","label":"SENAC","shape":"box"},{"id":"33469172000672","label":"SERV. NAC. DE APRENDIZAGEM COMERCIAL - SENAC","shape":"box"},{"id":"15068087000106","label":"sushi salada restaurante ltda me","shape":"box"},{"id":"13748617000131","label":"t e v ind e com de p\u00e3es e derivados ltda epp","shape":"box"},{"id":"13631053000152","label":"Tortaria Izabel Pinheiro LTDA","shape":"box"},{"id":"11792473000357","label":"GRANDE HOTEL DE LIMOEIRO","shape":"box"},{"id":"02575829000148","label":"Cia A\u00e9rea - AVIANCA","shape":"box"},{"id":"09296295000160","label":"Cia A\u00e9rea - AZUL","shape":"box"},{"id":"07575651000159","label":"Cia A\u00e9rea - GOL","shape":"box"},{"id":"02012862000160","label":"Cia A\u00e9rea - TAM","shape":"box"},{"id":94062641453.0,"label":"ROSINHA DA ADEFAL","shape":"circle"}]