[{"id":"04874449000130","label":"AGABO COMERCIO E SERVICOS LTDA - EPP","shape":"box"},{"id":"09046393000149","label":"ARMARINHO 25 DE AGOSTO LTDA","shape":"box"},{"id":"21406374000181","label":"D. DO CARMO GONCALVES DO NASCIMENTO FOTOCOPIAS - ME","shape":"box"},{"id":"32623895791","label":"eliane de souza dardinha","shape":"box"},{"id":"13345728000105","label":"EMYSOUTO PAPELARIA E INFORM\u00c1TICA","shape":"box"},{"id":"23253187000130","label":"IDEAL/LIMP COMERCIO DE MATERIAL DE LIMPEZA EIRELI","shape":"box"},{"id":"43283811004813","label":"KALUNGA COMERCIO E IND. GRAFICA LTDA","shape":"box"},{"id":"60444437000146","label":"LIGHT SERVICOS DE ELETRICIDADE S A","shape":"box"},{"id":"12132854000100","label":"WM COMERCIO DE ARTIGOS DE PAPELARIA LTDA-ME","shape":"box"},{"id":"24373856000170","label":"ALIANCA BEIRA RIO COMERCIO DE GNV LTDA","shape":"box"},{"id":"39194238000130","label":"AP GAS","shape":"box"},{"id":"33409525000134","label":"AUTO POSTO DE SERVI\u00c7OS AMA LTDA","shape":"box"},{"id":"04923368000182","label":"AUTO POSTO DE SERVI\u00c7OS ELITE DE MADUREIRA LTDA","shape":"box"},{"id":"36538973000126","label":"AUTO POSTO DE SERVI\u00c7OS SHOPING MADUREIRA","shape":"box"},{"id":"32589954000178","label":"AUTO POSTO ESTRELA DE CAXIAS LTDA","shape":"box"},{"id":"68575349000195","label":"AUTO POSTO GNOMO","shape":"box"},{"id":"39413174000111","label":"AUTO POSTO JARDIM CARIOCA","shape":"box"},{"id":"14580974000104","label":"AUTO POSTO LAGUNA LTDA","shape":"box"},{"id":"11086811000173","label":"AUTO POSTO SAO JUDAS TADEU LTDA","shape":"box"},{"id":"00306597003031","label":"Cascol Combust\u00edveis para Ve\u00edculos Ltda","shape":"box"},{"id":"00306597004607","label":"CASCOL COMBUST\u00cdVEIS PARA VE\u00cdCULOS LTDA","shape":"box"},{"id":"00306597006308","label":"CASCOL COMBUSTIVEIS PARA VEICULOS LTDA","shape":"box"},{"id":"00306597005328","label":"Cascol Combust\u00edveis para Ve\u00edculos Ltda.","shape":"box"},{"id":"00306597003627","label":"CASCOL COMBUSTIVEL","shape":"box"},{"id":"31423015000196","label":"COMERCIAL H KARL ALLERS LTDA","shape":"box"},{"id":"00543213000240","label":"DISBRAVE COMBUSTIVEIS LTDA","shape":"box"},{"id":"30603146000192","label":"DUCK POSTO DE GASOLINA PECAS E ACESSORIOS LTDA","shape":"box"},{"id":"17455879000169","label":"GUERREIROS DE CAXIAS POSTO DE GASOLINA LTDA","shape":"box"},{"id":"08111678000153","label":"HELIO PRATES COMERCIO DE COMBUSTIVEIS E DERIVADOS LTDA","shape":"box"},{"id":"07396700000196","label":"LORD RODRIGO COMERCIO DE COMBUSTIVEIS LTDA","shape":"box"},{"id":"00498021000189","label":"MARGARIDA DE RIO CLARO AUTO POSTO LTDA","shape":"box"},{"id":"07481349000131","label":"P0STO DE COMBUSTIVEL CONFORTACO LTDA","shape":"box"},{"id":"00624712000181","label":"PERALTA'S POSTO DE SERVICOS LTDA","shape":"box"},{"id":"33495169000119","label":"POSTO DE GASOLINA CENTEN\u00c1RIO","shape":"box"},{"id":"09297883000118","label":"POSTO DE GASOLINA ITAJUB\u00c1","shape":"box"},{"id":"03087284000193","label":"POSTO DE SERVI\u00c7OS BIG DUTRA","shape":"box"},{"id":"10750039000180","label":"POSTO DISBRAVE IMPERIAL LTDA","shape":"box"},{"id":"30068589000120","label":"POSTO GUITY LTDA","shape":"box"},{"id":"00314831000138","label":"POSTO ITAMARATY LTDA","shape":"box"},{"id":"01648535000136","label":"POSTO LUC PADUA LTDA","shape":"box"},{"id":"29319530000189","label":"POSTO MORGADO LTDA","shape":"box"},{"id":"03888413000142","label":"POSTO PIONEIRO CAPIVARI","shape":"box"},{"id":"18055554000151","label":"POSTO Z+Z 314 SUL LTDA","shape":"box"},{"id":"06057223000848","label":"SENDAS","shape":"box"},{"id":"32511032000148","label":"SILPIR COMERCIO E SERVI\u00c7OS LTDA","shape":"box"},{"id":"29017407000103","label":"SOCAPE SOCIEDADE CAXIENSE DE PETROLEO LTDA","shape":"box"},{"id":"21793072000103","label":"CARVALHO DA SILVA ADVOGADOS","shape":"box"},{"id":"05205920000160","label":"LINCE ASSESSORIA E CONSULTORIA LTDA - ME","shape":"box"},{"id":"09520337000102","label":"BAIXADA CRYSTAL ORGANIZA\u00c7AO JORNALISTICA LTDA","shape":"box"},{"id":"72072473000105","label":"BEZERRA BEL EDITORES LTDA","shape":"box"},{"id":"17314329004893","label":"BRASILIA VIENA CAFE","shape":"box"},{"id":"11244751000170","label":"CAPITAL EMPRESA JORNALISTICA EIRELI","shape":"box"},{"id":"02582698000126","label":"CATHAY COM E COMUNICA\u00c7\u00c3O LTDA.","shape":"box"},{"id":"32907388000103","label":"COPIADORA EXATA LTDA","shape":"box"},{"id":"01164836000194","label":"esteio editora com\u00e9rcio e presta\u00e7\u00e3o de servi\u00e7os ltda","shape":"box"},{"id":"14776057000515","label":"FAMA EMPREENDIMENTOS ALIMENTICIOS LTDA EPP","shape":"box"},{"id":"13915951000132","label":"G & R COMUNICACAO LTDA - ME","shape":"box"},{"id":"01829226000162","label":"GR\u00c1FICA PAPELARIA E CARIMBARIA MAN\u00c1 BETEL LTDA","shape":"box"},{"id":"02495060000158","label":"Imprint 2001 Grafica e Editora Ltda","shape":"box"},{"id":"16554291000108","label":"KI VISUAL XRV MOLDURAS LTDA","shape":"box"},{"id":"09341833000190","label":"KRIA PUBLICIDADE E PROPAGANDA LTDA - ME","shape":"box"},{"id":"33469172000672","label":"LANCHONETE SENAC","shape":"box"},{"id":"14002956000137","label":"MIDIA DE PAPEL EDITORA E PUBLICIDADE LTDA","shape":"box"},{"id":"17732582000101","label":"MULTIMIDIA COMUNICA\u00c7\u00c3O INTEGRADA","shape":"box"},{"id":"10556536000141","label":"PLANETA BAIXADA ORGANIZACOES JORNALISTICAS LTDA - ME","shape":"box"},{"id":"40381204000134","label":"POOL ARTES GR\u00c1FICAS LTDA","shape":"box"},{"id":"27036541000126","label":"TL FRANCA EDITORA LTDA - EPP","shape":"box"},{"id":"07575651000159","label":"Gol - Linhas A\u00e9reas Inteligentes","shape":"box"},{"id":"00000000000001","label":"CELULAR FUNCIONAL","shape":"box"},{"id":"40432544006269","label":"CLARO S.A","shape":"box"},{"id":"05423963000111","label":"OI M\u00f3vel S.A.","shape":"box"},{"id":"00000000000006","label":"RAMAL","shape":"box"},{"id":"02558157001487","label":"TELEFONICA BRASIL S.A.","shape":"box"},{"id":"00000000000007","label":"CORREIOS - CARTA REGISTRADA","shape":"box"},{"id":"29317740000138","label":"ECT","shape":"box"},{"id":"34028316068336","label":"ECT","shape":"box"},{"id":"34028316064691","label":"EMP BRAS DE CORREIOS E TELEGRAFOS","shape":"box"},{"id":"04735670000107","label":"EDITORA CONFIAN\u00c7A LTDA - CARTA CAPITAL","shape":"box"},{"id":"28116614000152","label":"54S. K. PIZZARIA E RESTAURANTE LTDA","shape":"box"},{"id":"18196186000161","label":"BAR E RESTAURANTE GRILLET","shape":"box"},{"id":"33125287000135","label":"Bar e Restaurante S\u00e3o Sebasti\u00e3o da Vila Ltda","shape":"box"},{"id":"03156803000128","label":"BIG DUTRA FAST FOOD LTDA","shape":"box"},{"id":"14017781000301","label":"C GOMES DOS SANTOS RESTAURANTES E LANCHONETES - ME","shape":"box"},{"id":"33089780000147","label":"CAF\u00c9 E BAR AEROPORTO SANTOS DUMONT LTDA","shape":"box"},{"id":"31130537000280","label":"CASA DO ALEMAO","shape":"box"},{"id":"31130537000361","label":"CASA DO ALEMAO  INDUSTRIA E COM DE LANCHES LTDA","shape":"box"},{"id":"31130537000795","label":"CASA DO ALEM\u00c3O INDUSTRIAL E COM. DE LANCHES","shape":"box"},{"id":"30710107000194","label":"CASA DO MAM\u00c3O","shape":"box"},{"id":"74552068001353","label":"CPQ BRASIL S/A","shape":"box"},{"id":"74552068001434","label":"CPQ BRASIL S/A","shape":"box"},{"id":"74552068002082","label":"CPQ BRASIL S/A","shape":"box"},{"id":"15562279000174","label":"EMPORIO PARATY CAF\u00c9 E MERCEARIA LTDA","shape":"box"},{"id":"10841547001145","label":"F & L EMPREENDIMENTOS COMERCIAIS LTDA-ME","shape":"box"},{"id":"15575591000100","label":"FFV RESTAURANTE E SERVI\u00c7OS DE BUFFET LTDA","shape":"box"},{"id":"02905110020234","label":"GR SERVI\u00c7OS E ALIMENTA\u00c7\u00c3O LTDA.","shape":"box"},{"id":"72513971000146","label":"IL NONNO GALETERIA LTDA","shape":"box"},{"id":"29810801000102","label":"KIS HOBBY CHOPP RESTAURANTE LTDA","shape":"box"},{"id":"31959877000138","label":"LANCHONENTE PARAISO DE RIO CLARO LTDA","shape":"box"},{"id":"01476168000130","label":"LANCHONETE E RESTAURANTE LIBANEZA LTDA","shape":"box"},{"id":"17820256000229","label":"M E R EMPRESA ALIMENT\u00cdCIA LTDA-EPP","shape":"box"},{"id":"19859870000491","label":"MFT Empreendimentos Aliment\u00edcios Eireli - ME","shape":"box"},{"id":"00493924000177","label":"ML - Alimenta\u00e7\u00e3o e Divers\u00f5es S/A","shape":"box"},{"id":"11869345000100","label":"NAPOLITANA COMERCIO DE ALIMENTOS LTDA - ME","shape":"box"},{"id":"17441911000238","label":"PAINEIRAS CAFETEIRA E COMECIO DE ALIMENTOS LTDA","shape":"box"},{"id":"17433775000153","label":"PLC COM\u00c9RCIO DE ALIMENTOS LTDA","shape":"box"},{"id":"01872334000118","label":"REI DO BACALHAU RESTAURANTE TEIXEIRA BATISTA TDA","shape":"box"},{"id":"05003056000113","label":"RESTAURANTE CRHISTINES LTDA","shape":"box"},{"id":"21579981000143","label":"RESTAURANTE ORIENTAL KITANO LTDA ME","shape":"box"},{"id":"24639420000180","label":"RESTAURANTE XELE GRILL EIRELLIEPP","shape":"box"},{"id":"33469172001644","label":"SERVI\u00c7O NACIONAL DE APRENDIZ. COMERCIAL SENAC","shape":"box"},{"id":"03346671000954","label":"TAIOBA SELF-SERVICE LTDA-EPP","shape":"box"},{"id":"18810751000139","label":"TRES IRMAS GASTRONOMIA LTDA ME","shape":"box"},{"id":"27033523000190","label":"Vila Francisca Alimentos e Bebidas LTDA","shape":"box"},{"id":"11796602001357","label":"E . HORTELARIA E TURISMO LTDA","shape":"box"},{"id":"21613382000107","label":"JEAN VILAR DOS SANTOS - ME","shape":"box"},{"id":"01029659000133","label":"COOPERATIVA DOS TAXISTAS DO TERMINAL RODOV.DE MACEIO","shape":"box"},{"id":"06794783000109","label":"COOPERFINS R\u00c1DIO T\u00c1XI CNF.","shape":"box"},{"id":"19944627000200","label":"ESTAKI ESTACIONAMENTOS LTDA","shape":"box"},{"id":"01076436000127","label":"RADIO TAXI SAO JOSE","shape":"box"},{"id":"26050819000157","label":"SELETO VILA BUSINESS HOTEL LTDA","shape":"box"},{"id":"02575829000148","label":"Cia A\u00e9rea - AVIANCA","shape":"box"},{"id":"09296295000160","label":"Cia A\u00e9rea - AZUL","shape":"box"},{"id":"02012862000160","label":"Cia A\u00e9rea - TAM","shape":"box"},{"id":47712244987.0,"label":"CELSO PANSERA","shape":"circle"}]