[{"id":"02558157000162","label":"Telef\u00f4nica Brasil S. A. VIVO","shape":"box"},{"id":"20745720000193","label":"Abdalla Combustiveis Ltda","shape":"box"},{"id":"10978814000159","label":"Posto 10 Comercio de Combustiveis Ltda","shape":"box"},{"id":"00000000000001","label":"CELULAR FUNCIONAL","shape":"box"},{"id":"40432544043628","label":"CLARO","shape":"box"},{"id":"00000000000006","label":"RAMAL","shape":"box"},{"id":"00000000000007","label":"CORREIOS - CARTA COMERCIAL","shape":"box"},{"id":1611500125.0,"label":"ROBERTO BALESTRA","shape":"circle"}]