[{"id":"61695227000193","label":"ELETROPAULO METROPOLITANA DE S\u00c3O PAULO S/A","shape":"box"},{"id":"62779145000190","label":"Irmandade sta casa Misericordia sp","shape":"box"},{"id":"62268966000161","label":"AGUA FUNDA SERVICOS AUTOMOTIVOS LTDA","shape":"box"},{"id":"09460889000164","label":"ANEX AUTOMOTIVO LTDA","shape":"box"},{"id":"15831038000183","label":"AUTO POSTO VILA URUPES LTDA","shape":"box"},{"id":"00005892000113","label":"ML SOUZA & CIA LTDA","shape":"box"},{"id":"09613772000173","label":"CONDE & DELL ARINGA - DES DE SOFTWARES","shape":"box"},{"id":"04835124000148","label":"OZZYMANDHAS DIGITACAO DE TEXTOS LTDA ME","shape":"box"},{"id":"29093334000139","label":"PEDRO GUSTAVO AUBERT","shape":"box"},{"id":"02012862000160","label":"TAM LINHAS AEREAS S/A.","shape":"box"},{"id":"00000000000001","label":"CELULAR FUNCIONAL","shape":"box"},{"id":"40432544000147","label":"CLARO S/A - NET","shape":"box"},{"id":"00000000000006","label":"RAMAL","shape":"box"},{"id":"02558157000162","label":"Telef\u00f4nia Brasil S/A","shape":"box"},{"id":"03953506000103","label":"BELINI PAES E GASTRONOMIA","shape":"box"},{"id":"10923812000162","label":"MARZUK COM. DE ALIMENTOS LTDA ME","shape":"box"},{"id":"15695357000109","label":"ASSOCIA\u00c7\u00c3O DOS TAXISTAS DO DISTRITO FEDERAL","shape":"box"},{"id":"00031708000100","label":"SINPETAXI","shape":"box"},{"id":"31024314000158","label":"Vou de Taxi","shape":"box"},{"id":"07575651000159","label":"Cia A\u00e9rea - GOL","shape":"box"},{"id":"07523555000167","label":"enel","shape":"box"},{"id":"62816798000100","label":"HUBERT IMOVEIS E ADMINISTRACAO LTDA","shape":"box"},{"id":"62779145000602","label":"IRMANDADE STA CASA M.S.PAULO","shape":"box"},{"id":"31180570000134","label":"Lucas Paulino de Sousa Nogueira","shape":"box"},{"id":"58662446000161","label":"AUTO POSTO 4 R LTDA","shape":"box"},{"id":"08877175000193","label":"AUTO POSTO AGULHAS NEGRAS LTDA","shape":"box"},{"id":"60830569000106","label":"AUTO POSTO CARDEAL LTDA","shape":"box"},{"id":"52024882000129","label":"AUTO POSTO CHEGADA LTDA","shape":"box"},{"id":"07846558000131","label":"AUTO POSTO DUQUE SALIM MALUF LTDA","shape":"box"},{"id":"06923355000139","label":"AUTO POSTO ILHA VERDE LTDA","shape":"box"},{"id":"20461964000144","label":"AUTO POSTO MISSOES KM 285 LTDA","shape":"box"},{"id":"02646144000145","label":"AUTO POSTO NOVO CENTRO LTDA","shape":"box"},{"id":"61265153000155","label":"AUTO POSTO SENA MADUREIRA LTDA","shape":"box"},{"id":"07084739000178","label":"AUTO POSTO VASSUNUNGA LTDA","shape":"box"},{"id":"07745105000119","label":"CAMPEAO 28 POSTO DE SERVICOS LTDA","shape":"box"},{"id":"00306597003112","label":"CASCOL COMBUSTIVEIS PARA VEICULOS LTDA","shape":"box"},{"id":"02159918000103","label":"CENTER SERVICE M JUNQUEIRA LT","shape":"box"},{"id":"24383829000189","label":"CENTRO AUTOMOTIVO NOVA PAULISTA LTDA","shape":"box"},{"id":"66563081000146","label":"CENTRO AUTOMOTIVO PARAISO LT","shape":"box"},{"id":"63028476000150","label":"DUTRAO AUTO POSTO LT","shape":"box"},{"id":"14929417000148","label":"FELIX FAGUNDES POSTO AUTOMOTIVO LTDA","shape":"box"},{"id":"02024254000175","label":"LIPASA AUTO POSTO DE SERVICOS LTDA","shape":"box"},{"id":"48770051000129","label":"MIRACATU AUTO POSTO LT","shape":"box"},{"id":"72911837000950","label":"ORGANIZACAO COMERCIAL LAGO AZUL LTDA","shape":"box"},{"id":"09386909000102","label":"POSTO COMERCIAL UNB LTDA","shape":"box"},{"id":"60659554000127","label":"POSTO DE SERVICO CAMACHO LT","shape":"box"},{"id":"11071082000181","label":"SILVIA MARIA PINTO SANTOS","shape":"box"},{"id":"21504196000121","label":"SOCIEDADE COMERCIAL CANAA -LTDA","shape":"box"},{"id":"08422103000151","label":"F.Y. SAKAI","shape":"box"},{"id":"23425589000175","label":"PARLABRASIL EIRELI","shape":"box"},{"id":"09296295001484","label":"AZUL LINHAS A\u00c9REAS BRASILEIRAS S.A.","shape":"box"},{"id":"09296295000160","label":"AZUL LINHAS A\u00c9REAS INTELIGENTES S.A","shape":"box"},{"id":"06164253000187","label":"GOL LINHAS AEREAS INTELIGENTES S.A.","shape":"box"},{"id":"00000000000007","label":"CORREIOS - CARTA COMERCIAL","shape":"box"},{"id":"34028316107099","label":"EMPRESA BRASILEIRA DE CORREIOS E TELEGRAFOS","shape":"box"},{"id":"60909215000151","label":"ALMANARA RESTAURANTES E LANCHONETES LTDA","shape":"box"},{"id":"20802001000167","label":"AO BAR GUANABARA RESTAURANTE LTDA","shape":"box"},{"id":"24334147000186","label":"BISTRO DA ENOTECA EIRELI","shape":"box"},{"id":"07747151000157","label":"Embaixador Prime Hotel Ltda.","shape":"box"},{"id":"96390521000171","label":"ESTADAO GRILL CHURRASCARIA LTDA","shape":"box"},{"id":"23406188000178","label":"GREENS FOODS LTDA","shape":"box"},{"id":"05202077000753","label":"JLM RESTAURANTE LTDA EPP","shape":"box"},{"id":"24188337000213","label":"MJS RESTAURANTES EIRELI - EPP","shape":"box"},{"id":"05235624000101","label":"PAES E DOCES DA VILA LTDA","shape":"box"},{"id":"61906087000155","label":"PANIFICADORA PALMA DE OURO DO CENTRO EIRELI","shape":"box"},{"id":"09054158000119","label":"PBJM COMERCIO DE GENEROS ALIMENTICIOS LTDA","shape":"box"},{"id":"11899228000181","label":"PECORINOX BAR RESTAURANTE TABACARIA E EVENTOS LTD","shape":"box"},{"id":"05681997000106","label":"RITA DE CASSIA C CABRERA LANCHONETE","shape":"box"},{"id":"09550214000106","label":"SERRANA COMERCIO DE ALIMENTOS LTDA","shape":"box"},{"id":"33469172000672","label":"SERVICO NACIONAL DE APRENDIZAGEM COMERCIAL SENAC","shape":"box"},{"id":"33469172001644","label":"SERVICO NACIONAL DE APRENDIZAGEM COMERCIAL SENAC","shape":"box"},{"id":"33469172002292","label":"SERVICO NACIONAL DE APRENDIZAGEM COMERCIAL SENAC","shape":"box"},{"id":"07286731000194","label":"SILT SELF SERVICE EIRELI ME","shape":"box"},{"id":"61365508000188","label":"SUPERMERCADO ESTADOS UNIDOS LTDA","shape":"box"},{"id":"24346446000211","label":"ZTUNES ALIMENTACAO EIRELI","shape":"box"},{"id":"04477091000101","label":"ELIZEU MASAHARU OHTA-EPP","shape":"box"},{"id":"09967852010009","label":"HOTELARIA ACCOR BRASIL S/A","shape":"box"},{"id":"80732928003034","label":"Ibis Atrios Hoteis S.A","shape":"box"},{"id":"12939971000180","label":"MARC  CENTER  HOTEL  LTDA","shape":"box"},{"id":"05012173000143","label":"PREFEITURA DO MUNIC\u00cdPIO DE PERU\u00cdBE","shape":"box"},{"id":"06033835000205","label":"VITRINE EMPREENDIMENTOS LTDA","shape":"box"},{"id":"02509186000134","label":"AB TRIANGULO","shape":"box"},{"id":"02679185000138","label":"AUTOVIAS S/A","shape":"box"},{"id":"02451848000162","label":"CONC. SISTEMA ANHANGUERA-BANDEIRANTES S/A","shape":"box"},{"id":"00521294000105","label":"COOPERATIVA DOS CONDUTORES AUTONOMOS DE BRASILIA LTDA","shape":"box"},{"id":"38069159000135","label":"COOPERATIVA DOS TAXISTAS AUT. DO DIST. FEDERAL","shape":"box"},{"id":"18992233000183","label":"RADIO TAXI SHALOM LTDA - EPP","shape":"box"},{"id":"04088208000165","label":"SEM PARAR","shape":"box"},{"id":"07424109000103","label":"SINTAXI/DF","shape":"box"},{"id":"12623662000105","label":"UNITAXI DF","shape":"box"},{"id":"44581056000152","label":"MANOEL RODRIGUES","shape":"box"},{"id":"45992724002493","label":"RAPIDO CAMPINAS","shape":"box"},{"id":"45992724000105","label":"r\u00e1pido luxo campinas ltda","shape":"box"},{"id":"02575829000148","label":"Cia A\u00e9rea - AVIANCA","shape":"box"},{"id":"00512777000135","label":"Cia A\u00e9rea - PASSAREDO","shape":"box"},{"id":2441369806.0,"label":"Paulo Teixeira","shape":"circle"}]