[{"id":"00837901000132","label":"BAYEUX & LOUREN\u00c7O ASSOCIADOS LTDA.","shape":"box"},{"id":"06226820000182","label":"CENTER PAPEIS COMERCIAL LTDA","shape":"box"},{"id":"40432544000147","label":"CLARO S.A - NET","shape":"box"},{"id":"07014367000103","label":"CONSULTWEB","shape":"box"},{"id":"61695227000193","label":"ELETROPAULO METROPOLITANA ELETRICIDADE DE S\u00c3O PAULO S.A.","shape":"box"},{"id":"66902628000190","label":"LUCYS PEL PAPELARIA","shape":"box"},{"id":"07339090000199","label":"MULT PAPELARIA","shape":"box"},{"id":"43776517000180","label":"SABESP","shape":"box"},{"id":"00320065000114","label":"WORKS INFROMATICA COMERCIAL LTDA - EPP","shape":"box"},{"id":"01258154000140","label":"96 AUTO POSTO LTDA","shape":"box"},{"id":"00728403000151","label":"AUTO POSTO AVENIDA DE ANDRADRINA LTDA","shape":"box"},{"id":"04007304000131","label":"AUTO POSTO BARAO DE ANDRADINA LTDA","shape":"box"},{"id":"44783579000181","label":"AUTO POSTO BARRETOS LTDA","shape":"box"},{"id":"19508812000170","label":"AUTO POSTO COBRA 121 LTDA","shape":"box"},{"id":"48794085000153","label":"AUTO POSTO MAKARI LTDA","shape":"box"},{"id":"43513001000142","label":"AUTO POSTO MONTANA LT","shape":"box"},{"id":"64584972000153","label":"AUTO POSTO RODEIO BARRETOS LTDA","shape":"box"},{"id":"45099165000109","label":"AUTO POSTO UNIVERSITARIO LTDA","shape":"box"},{"id":"61343737000100","label":"POSTO TOPAZIO LTDA","shape":"box"},{"id":"44071306000104","label":"SOFTCAR - SERVI\u00c7OS AUTOMOTIVOS E COM. LT","shape":"box"},{"id":"62658786000196","label":"TROPICAL GASOLINAS E SERV. AUTOMOTIVOS LTDA.","shape":"box"},{"id":"18684095000175","label":"ISSY E CAMARGOS ADVOGADOS","shape":"box"},{"id":"10748852000115","label":"ARTES GR\u00c1FICAS ENTRELINHAS LTDA","shape":"box"},{"id":"19640456000144","label":"BRASIL IMPRESSO EIRIELLI","shape":"box"},{"id":"52821394000142","label":"GON\u00c7ALVES & FERRA LTDA-ME","shape":"box"},{"id":"00356213000150","label":"LEOGRAF GR\u00c1FICA E EDITORA LTDA","shape":"box"},{"id":"08345631000154","label":"M\u00c9DIA HOUSE COMUNICA\u00c7\u00d5ES E MARKETING","shape":"box"},{"id":"14838642000179","label":"MOVIMENTO WEB E ARTES GRAFICAS SS LTDA-ME","shape":"box"},{"id":"02575829000148","label":"AVIANCA","shape":"box"},{"id":"07575651000159","label":"GOL - LINHAS A\u00c9REAS S/A","shape":"box"},{"id":"00000000000001","label":"CELULAR FUNCIONAL","shape":"box"},{"id":"00000000000003","label":"IM\u00d3VEL FUNCIONAL","shape":"box"},{"id":"00000000000006","label":"RAMAL","shape":"box"},{"id":"02558157000162","label":"Telefonica Brasil S.A - VIVO","shape":"box"},{"id":"00000000000007","label":"CORREIOS - CARTA COMERCIAL","shape":"box"},{"id":"34028316225962","label":"ECT - EMP. BRAS. DE CORREIOS E TEL\u00c9GRAFOS","shape":"box"},{"id":"00319295000163","label":"GEPE EMPREENDIMENTOS DE HOTELARIA LTDA","shape":"box"},{"id":"05217384000627","label":"H PLUS ADMINISTRA\u00c7\u00c3O E HOTELARIA LTDA - SCP ATHOS BULCAO - HPLUS -ATHOS BULCAO","shape":"box"},{"id":"15800340000174","label":"MAXPRESS TRANSPORTES","shape":"box"},{"id":"18186505000158","label":"stillus transportes","shape":"box"},{"id":"01519135000120","label":"ASSOCIA\u00c7\u00c3O DE TAXISTAS PONTO 1783","shape":"box"},{"id":"13408274000166","label":"ASSOCIA\u00c7\u00c3O DO PONTO DE TAXI NOVA OL\u00cdMPIA - PONTO 2984","shape":"box"},{"id":"03114090000130","label":"ASSOCIA\u00c7\u00c3O DOS TAXISTAS DE BRAS\u00cdLIA - ATB","shape":"box"},{"id":"15695357000109","label":"ASSOCIA\u00c7\u00c3O DOS TAXISTAS DO DISTRITO FEDERAL - ASTDF","shape":"box"},{"id":"04088208000165","label":"CENTRO DE GEST\u00c3O DE MEIOS DE PAGAMENTOS S/A","shape":"box"},{"id":"02451848000162","label":"Conc. Sistema Anhanguera-Bandeirantes S/A","shape":"box"},{"id":"08046163000117","label":"COOPERTAXI","shape":"box"},{"id":"38069159000135","label":"COOPERTAXI","shape":"box"},{"id":"00031708000371","label":"SIND. DOS PERMISSIONARIOS DE TAXIS E MOTORISTAS AUX. DO DF","shape":"box"},{"id":"00031708000100","label":"SINPETAXI","shape":"box"},{"id":"07424109000103","label":"SINTAXI - DF","shape":"box"},{"id":"37990298000134","label":"T\u00e1xi Alvorada Ltda","shape":"box"},{"id":"12623662000105","label":"UniTaxiDF","shape":"box"},{"id":"08969988000103","label":"SERVENG TRANSPORTES LTDA","shape":"box"},{"id":"09296295000160","label":"Cia A\u00e9rea - AZUL","shape":"box"},{"id":"00512777000135","label":"Cia A\u00e9rea - PASSAREDO","shape":"box"},{"id":"02012862000160","label":"Cia A\u00e9rea - TAM","shape":"box"},{"id":56524455568.0,"label":"Orlando Silva","shape":"circle"}]