[{"id":"02341467000120","label":"AMAZONAS ENERGIA","shape":"box"},{"id":"10247876000190","label":"COPEL","shape":"box"},{"id":"00108786009898","label":"NET SERVI\u00c7OS DE COMUNICA\u00c7\u00c3O","shape":"box"},{"id":"04762808000167","label":"POLO MODAS E VARIEDADES LTDA","shape":"box"},{"id":"12310040000119","label":"PRA VOC\u00ca - DORABELI ARMARINHO E PAPELARIA LTDA","shape":"box"},{"id":"38408201204","label":"SYLVIO LIFSITCH BRASIL","shape":"box"},{"id":"33000118000179","label":"TELEMAR NORTE LESTE S/A","shape":"box"},{"id":"33000118000764","label":"TELEMAR NORTE LESTE S/A","shape":"box"},{"id":"00703298000104","label":"ABASTECE COMBUSTIVEIS","shape":"box"},{"id":"08202116000115","label":"AEROPORTO POSTO AEROPORTO LTDA","shape":"box"},{"id":"06006437000119","label":"AGUAS CLARAS POSTO DE SERVI\u00c7OS LTDA","shape":"box"},{"id":"38043832000168","label":"AMORIM COMERCIO DE DERIVADOS DE PETROLEO LTDA","shape":"box"},{"id":"37106895000153","label":"AUTO POSTO 107 SUL","shape":"box"},{"id":"03530749000139","label":"AUTO POSTO 314 NORTE LTDA","shape":"box"},{"id":"38076089000142","label":"AUTO POSTO AGUAS CLARAS LTDA","shape":"box"},{"id":"00692806000198","label":"AUTO POSTO AGUIA DE OURO LTDA","shape":"box"},{"id":"00000042000203","label":"AUTO POSTO GASOL LTDA","shape":"box"},{"id":"00000042000556","label":"AUTO POSTO GASOL LTDA","shape":"box"},{"id":"00000042000637","label":"AUTO POSTO GASOL LTDA","shape":"box"},{"id":"00814083000152","label":"AUTO POSTO IMPERIAL H SUXBERGER","shape":"box"},{"id":"02731610000271","label":"AUTO POSTO ITICAR LTDA","shape":"box"},{"id":"07129219000134","label":"AUTO POSTO JPC DERIVADOS DE PETROLEO LTDA","shape":"box"},{"id":"03261491000708","label":"AUTO POSTO MILENNIUM 2000","shape":"box"},{"id":"05000684000145","label":"AUTO POSTO PETER PAN 01","shape":"box"},{"id":"05000684000226","label":"AUTO POSTO PETER PAN 01 LTDA","shape":"box"},{"id":"00097626000400","label":"BRASAL COMBUSTIVEIS LTDA","shape":"box"},{"id":"00373589000335","label":"CAL COMBUSTIVEIS AUTOMOTIVOS LTDA","shape":"box"},{"id":"00661132000750","label":"CANA\u00c3 COMBUSTIVEIS PARA VE\u00cdCULOS LTDA","shape":"box"},{"id":"00038505000579","label":"CONVER COMBUSTIVEIS AUTOMITIVOS LTDA","shape":"box"},{"id":"00038505000650","label":"CONVER COMBUSTIVEIS AUTOMOTIVOS LTDA","shape":"box"},{"id":"00038505000226","label":"CONVER COMBUSTIVEIS REPRES. LTDA","shape":"box"},{"id":"00038505000145","label":"CONVER COMBUSTIVEIS VEICULOS REPRES","shape":"box"},{"id":"84493139000538","label":"CONVER COMERCIO E SERVI\u00c7OS LTDA","shape":"box"},{"id":"84519883000300","label":"D. L DE SOUZA & CIA LTDA","shape":"box"},{"id":"07821726000134","label":"DFM- DERIVADOS","shape":"box"},{"id":"00543213000240","label":"DISBRAVE IMPORTS LTDA","shape":"box"},{"id":"05900065000107","label":"FREDERICO C. P. CARVALHEIRA NETO","shape":"box"},{"id":"00038505000498","label":"GASOL","shape":"box"},{"id":"00306597000601","label":"GASOL","shape":"box"},{"id":"00306597000954","label":"GASOL","shape":"box"},{"id":"00373589000416","label":"GASOL","shape":"box"},{"id":"00306597001179","label":"GASOL COMBUSTIVEIS","shape":"box"},{"id":"00603738000305","label":"GASOL COMBUSTIVEIS AUTOMOTIVOS LTDA","shape":"box"},{"id":"00603738000658","label":"GASOL COMBUSTIVEIS AUTOMOTIVOS LTDA","shape":"box"},{"id":"01682336000144","label":"ITA LUCAS LTDA","shape":"box"},{"id":"37128477000167","label":"JT COMERCIO DE DERIVADOS DE PETROLEO LTDA","shape":"box"},{"id":"00038463000819","label":"LUBRIFICANTES GASOL INDUSTRIA E COM LTDA","shape":"box"},{"id":"00038463000738","label":"LUBRIFICANTES GASOL INDUSTRIA E COM. LTDA","shape":"box"},{"id":"02989654001197","label":"MELHOR POSTO DE COMBUSTIVEIS LTDA","shape":"box"},{"id":"02072286000146","label":"PETROIL","shape":"box"},{"id":"02072286000650","label":"PETROIL COMBUSTIVEIS LTDA","shape":"box"},{"id":"01691433000101","label":"PETROMAY DERIVADOS DE PETROLEO LTDA","shape":"box"},{"id":"00042044000184","label":"POLAR DERIVADOS DE PETROLEO LTDA","shape":"box"},{"id":"05158335000156","label":"POSTO 109 SUL DERIVADOS DE PETROLEO LTDA","shape":"box"},{"id":"07719588000187","label":"POSTO ABASTECE COM. DERIV. DE PETROLEO","shape":"box"},{"id":"01655778000525","label":"POSTO AGUAS CLARAS","shape":"box"},{"id":"09386909000102","label":"POSTO COMERCIAL UNB LTDA","shape":"box"},{"id":"04473193000159","label":"POSTO DA TORRE LTD","shape":"box"},{"id":"34274233004604","label":"POSTO ESCOLA SENAC","shape":"box"},{"id":"10750039000180","label":"POSTO IMPERIAL","shape":"box"},{"id":"01156523000194","label":"POSTO JADE","shape":"box"},{"id":"00358192000102","label":"POSTO MARISTA 409","shape":"box"},{"id":"00358192000293","label":"POSTO MARISTA 414","shape":"box"},{"id":"84519883000130","label":"POSTO MATRIZ","shape":"box"},{"id":"10988014000119","label":"POSTO PARQUE DEZ","shape":"box"},{"id":"09205835000152","label":"POSTO PETROMINAS","shape":"box"},{"id":"72587132000172","label":"POSTO SANTA ROSA","shape":"box"},{"id":"00797283000144","label":"RASOL COMERCIO DE DERIVADOS DE PETROLEO LTDA","shape":"box"},{"id":"05662975000107","label":"SMAFF","shape":"box"},{"id":"09232995000190","label":"METRO COMERCIAL DE COMBUSTIVEIS LTDA","shape":"box"},{"id":"84529098000169","label":"GRAFICA MODERNA","shape":"box"},{"id":"03090756000167","label":"AMAZONAVES T\u00c1XI A\u00c9REO LTDA","shape":"box"},{"id":"04984400000130","label":"CLEITO TAXI A\u00c9REO LTDA","shape":"box"},{"id":"84316421000116","label":"RIO BRANCO AEROTAXI LTDA","shape":"box"},{"id":"00000000000003","label":"IM\u00d3VEL FUNCIONAL","shape":"box"},{"id":"00000000000006","label":"RAMAL","shape":"box"},{"id":"04206050003872","label":"TIM","shape":"box"},{"id":"00000000000007","label":"CORREIOS - ENCOMENDA PAC","shape":"box"},{"id":"04816658000127","label":"EDITORA ANA C\u00c1SSIA LTDA","shape":"box"},{"id":"04354908000154","label":"JORNAL A CRITICA","shape":"box"},{"id":"08951434000189","label":"TERRA EDITORA E GR\u00c1FICA","shape":"box"},{"id":"08852144000188","label":"ARIA\u00da TOWERS PARINTINS","shape":"box"},{"id":"84664309000176","label":"HOTEL SA\u00daDE FLAT","shape":"box"},{"id":"01482727000115","label":"HOTEL TAKANA","shape":"box"},{"id":"04034294000123","label":"PINHEIRO PALACE HOTEL","shape":"box"},{"id":"13492673000158","label":"PITUBA PLAZA HOTEL","shape":"box"},{"id":"84517994000108","label":"POUSADA DA JIB\u00d3IA","shape":"box"},{"id":"10381841000140","label":"LOCADORA DE VEICULOS HERFAB LTDA","shape":"box"},{"id":"07145414000158","label":"CARLOS ARAUJO DE AGUIAR","shape":"box"},{"id":"05763730000168","label":"DELCIMAR M VALIM -ME","shape":"box"},{"id":"38010633000153","label":"VIA- DF RENT A CAR","shape":"box"},{"id":"07575651000159","label":"Cia A\u00e9rea - GOL","shape":"box"},{"id":"02012862000160","label":"Cia A\u00e9rea - TAM","shape":"box"},{"id":2581680210,"label":"FRANCISCO PRACIANO","shape":"circle"}]