[{"id":"02016440000162","label":"AES SUL DISTRIBUIDORA GA\u00daCHA DE ENERGIA LTDA","shape":"box"},{"id":"08467115000100","label":"CEEE - COMP EST DE DISTR DE ENERGIA ELETRICA","shape":"box"},{"id":"18375245000169","label":"Cleu Gomes lisboa","shape":"box"},{"id":"92691336000166","label":"CREDITO REAL IMOVEIS E CONDOMINIOS S/A","shape":"box"},{"id":"04563205000136","label":"FERNANDO MAGGIONI RUSSO","shape":"box"},{"id":"89250039000170","label":"IMIBILIARIA JAIR BEHR LTDA","shape":"box"},{"id":"92691336001057","label":"MARIO ESP LOC COM EMP GRUPO CREDITO REAL","shape":"box"},{"id":"33530486013379","label":"NET SERVI\u00c7OS DE COMUNICA\u00c7\u00c3O S.A","shape":"box"},{"id":"00108786007410","label":"NET SERVI\u00c7OS DE COMUNICA\u00c7\u00c3O S/A","shape":"box"},{"id":"04078750000137","label":"PRUMOS INTERATIVA LTDA","shape":"box"},{"id":"01319851000164","label":"SISNETTI INTEGRADORA DE SOLU\u00c7\u00d5ES LTDA-ME","shape":"box"},{"id":"08694886000122","label":"WILD IM\u00d3VEIS","shape":"box"},{"id":"02346268000377","label":"A F COMERCIAL DE COMBUSTIVEIS LTDA","shape":"box"},{"id":"10673262000170","label":"A.L.P.COMERCIO DE COMB. LTDA","shape":"box"},{"id":"73856155000106","label":"AUTO POSTO GAUCHO LTDA","shape":"box"},{"id":"00306597003112","label":"BR  PETROBRAS","shape":"box"},{"id":"00097626000400","label":"BRASAL COMBUST\u00edVEIS LTDA","shape":"box"},{"id":"00306597001098","label":"CASCOL COMBUST\u00cdVEIS PARA VE\u00cdCULOS LTDA","shape":"box"},{"id":"00306597001250","label":"CASCOL COMBUSTIVEIS PARA VEICULOS LTDA","shape":"box"},{"id":"00306597002736","label":"CASCOL COMBUSTIVEIS PARA VEICULOS LTDA","shape":"box"},{"id":"00306597007100","label":"CASCOL COMBUST\u00cdVEIS PARA VE\u00cdCULOS LTDA","shape":"box"},{"id":"04340316000264","label":"COM. DE COMB. PADOIN LTDA","shape":"box"},{"id":"04340316000183","label":"COM\u00c9RCIO DE COMB OADOIN LTDA","shape":"box"},{"id":"00012211000144","label":"DRIVE CAR - TRANSPORTES E COMBUSTIVEIS LTDA","shape":"box"},{"id":"06071706000120","label":"PETRONORTE COMBUST\u00cdVEIS LTDA.","shape":"box"},{"id":"97663728006095","label":"Posto Cotrisoja","shape":"box"},{"id":"15680284000181","label":"Posto G1","shape":"box"},{"id":"00306597008696","label":"POSTO IPIRANGA","shape":"box"},{"id":"05625571000135","label":"Posto MK 107  Norte Ltda","shape":"box"},{"id":"00306597003201","label":"POSTO PETROBRAS 305 NORTE","shape":"box"},{"id":"00306597007290","label":"POSTO PETROBRAS 403 SUL","shape":"box"},{"id":"03229863000123","label":"POSTO ROTA DO SUL","shape":"box"},{"id":"16924825000132","label":"Conlegis","shape":"box"},{"id":"72113046000128","label":"STUDIO PESQUISAS E CONSULTORIA LTDA","shape":"box"},{"id":"90487430000172","label":"CARLOS HUMBERTO DELEVATI","shape":"box"},{"id":"02715976000176","label":"GRAF\u00cdCA CAMOBI LTDA","shape":"box"},{"id":"88729629000118","label":"GRAFICA JORNAL DAS MISS\u00d5ES LTDA","shape":"box"},{"id":"04658310000159","label":"VERS\u00c1TIL ARTES GR\u00c1FICAS","shape":"box"},{"id":"05423963000111","label":"14 BRASIL TELECOM CELULAR S/A","shape":"box"},{"id":"05423963000545","label":"14 BRASIL TELECOM CELULAR S/A","shape":"box"},{"id":"04206050005140","label":"3TIM CELULAR S.A.","shape":"box"},{"id":"33530486000129","label":"embratel","shape":"box"},{"id":"00000000000003","label":"IM\u00d3VEL FUNCIONAL","shape":"box"},{"id":"76535764000143","label":"OI S.A","shape":"box"},{"id":"76535764000224","label":"OI S.A","shape":"box"},{"id":"00000000000006","label":"RAMAL","shape":"box"},{"id":"04206050000180","label":"TIM CELULAR S.A.","shape":"box"},{"id":"00000000000007","label":"CORREIOS - CARTA COMERCIAL","shape":"box"},{"id":"92228048000170","label":"ALTERNATIVA","shape":"box"},{"id":"94070190000167","label":"Lomar Ve\u00edculos Ltda","shape":"box"},{"id":"02575829000148","label":"Cia A\u00e9rea - AVIANCA","shape":"box"},{"id":"09296295000160","label":"Cia A\u00e9rea - AZUL","shape":"box"},{"id":"07575651000159","label":"Cia A\u00e9rea - GOL","shape":"box"},{"id":"02012862000160","label":"Cia A\u00e9rea - TAM","shape":"box"},{"id":42844924034.0,"label":"Paulo Pimenta","shape":"circle"}]